{
  "melhores_notebooks": [
    {
      "posicao": 1,
      "modelo": "ASUS Vivobook 15 X1504VA",
      "preco": "R$ 3.199,00",
      "link": "https://www.google.com/search?q=ASUS+Vivobook+15+X1504VA+i5-1334U+16GB+512GB+SSD+preço+brasil",
      "foto": "https://m.media-amazon.com/images/I/71R2H04p54L._AC_SL1500_.jpg",
      "cpu": "Intel Core i5-1334U",
      "ram": "16 GB DDR4",
      "ssd": "512 GB NVMe SSD",
      "tela": "IPS Full HD",
      "analise": "Excelente custo-benefício com processador de 13ª geração e boa quantidade de RAM e SSD para produtividade e uso diário. A tela IPS é um diferencial na faixa de preço.",
      "notas": {
        "performance": 8,
        "tela": 9,
        "custo_beneficio": 10
      }
    },
    {
      "posicao": 2,
      "modelo": "Samsung Galaxy Book4 (i5-1335U)",
      "preco": "R$ 3.499,00",
      "link": "https://www.google.com/search?q=Samsung+Galaxy+Book4+i5-1335U+8GB+256GB+SSD+preço+brasil",
      "foto": "https://m.media-amazon.com/images/I/71X8gUjQ4wL._AC_SL1500_.jpg",
      "cpu": "Intel Core i5-1335U",
      "ram": "8 GB DDR4",
      "ssd": "256 GB NVMe SSD",
      "tela": "IPS Full HD",
      "analise": "Design premium e leve, ideal para portabilidade. O processador de 13ª geração oferece bom desempenho para tarefas cotidianas e profissionais. A tela IPS garante ótima qualidade de imagem.",
      "notas": {
        "performance": 8,
        "tela": 9,
        "custo_beneficio": 9
      }
    },
    {
      "posicao": 3,
      "modelo": "Acer Aspire 5 A515-45 (Ryzen 5 5500U)",
      "preco": "R$ 2.999,00",
      "link": "https://www.google.com/search?q=Acer+Aspire+5+A515-45+Ryzen+5+5500U+16GB+512GB+SSD+preço+brasil",
      "foto": "https://m.media-amazon.com/images/I/71k4vQ1g9fL._AC_SL1500_.jpg",
      "cpu": "AMD Ryzen 5 5500U",
      "ram": "16 GB DDR4",
      "ssd": "512 GB NVMe SSD",
      "tela": "IPS Full HD",
      "analise": "Um dos melhores em custo-benefício, com processador Ryzen 5, 16GB de RAM e 512GB de SSD, excelente para multitarefas e produtividade. A tela IPS é um grande atrativo.",
      "notas": {
        "performance": 8,
        "tela": 8,
        "custo_beneficio": 9
      }
    },
    {
      "posicao": 4,
      "modelo": "Lenovo IdeaPad Slim 3i (Core i5-13420H)",
      "preco": "R$ 3.650,00",
      "link": "https://www.google.com/search?q=Lenovo+IdeaPad+Slim+3i+Core+i5-13420H+8GB+512GB+SSD+preço+brasil",
      "foto": "https://m.media-amazon.com/images/I/61M4RjF6jKL._AC_SL1500_.jpg",
      "cpu": "Intel Core i5-13420H",
      "ram": "8 GB DDR4",
      "ssd": "512 GB NVMe SSD",
      "tela": "IPS Full HD",
      "analise": "Com um processador Intel Core i5 de 13ª geração da linha H, este notebook oferece desempenho superior para tarefas mais exigentes. A tela IPS e o design fino são pontos fortes.",
      "notas": {
        "performance": 9,
        "tela": 8,
        "custo_beneficio": 8
      }
    },
    {
      "posicao": 5,
      "modelo": "VAIO FE 16 (Ryzen 7 5825U)",
      "preco": "R$ 3.799,00",
      "link": "https://www.google.com/search?q=VAIO+FE+16+Ryzen+7+5825U+16GB+256GB+SSD+preço+brasil",
      "foto": "https://m.media-amazon.com/images/I/711jQe4p8hL._AC_SL1500_.jpg",
      "cpu": "AMD Ryzen 7 5825U",
      "ram": "16 GB DDR4",
      "ssd": "256 GB NVMe SSD",
      "tela": "IPS Full HD 16 polegadas",
      "analise": "Tela grande de 16 polegadas com painel IPS antirreflexo e um potente Ryzen 7, ideal para quem busca produtividade e espaço de trabalho. A autonomia de bateria também é um destaque.",
      "notas": {
        "performance": 9,
        "tela": 9,
        "custo_beneficio": 8
      }
    }
  ]
}